bright_cli/__init__.py
bright_cli-0.1.0.dist-info/WHEEL
bright_cli-0.1.0.dist-info/entry_points.txt
bright_cli-0.1.0.dist-info/METADATA
bright_cli-0.1.0.dist-info/RECORD
