Metadata-Version: 2.3
Name: bright-cli
Version: 0.1.0
Summary: Thin wrapper around Bright Data Web Unlocker HTTP API
Author: Benjamin Anderson
Author-email: Benjamin Anderson <andersonbcdefg@gmail.com>
Requires-Dist: aiohttp>=3.9.0
Requires-Dist: pandas>=2.0.0
Requires-Dist: python-dotenv>=1.0.0
Requires-Python: >=3.13
